assets
html2pdf_converter
static
templates
