Metadata-Version: 1.1
Name: opportini-pdfbuilder
Version: 0.3.0
Summary: HTML to PDF with Python-Jinja
Home-page: https://github.com/competition-index/opportini_html2pdf/
Author: Menno
Author-email: phoenix.ts1991@gmail.com
License: UNKNOWN
Platform: UNKNOWN
Classifier: Development Status :: 3 - Alpha
Classifier: Intended Audience :: Developers
Classifier: License :: OSI Approved :: MIT License
Classifier: Programming Language :: Python :: 3.5
